Metadata-Version: 2.1
Name: aiortc-datachannel-only
Version: 1.3.2.post3
Summary: Jeremy Lainé's aiortc library with only datachannel support and no extra dependencies
Home-page: https://github.com/ollipal/aiortc-datachannel-only
Author: Olli Paloviita
Author-email: olli.paloviita@gmail.com
License: BSD
Platform: UNKNOWN
Classifier: Development Status :: 5 - Production/Stable
Classifier: Environment :: Web Environment
Classifier: Intended Audience :: Developers
Classifier: License :: OSI Approved :: BSD License
Classifier: Operating System :: OS Independent
Classifier: Programming Language :: Python
Classifier: Programming Language :: Python :: 3
Classifier: Programming Language :: Python :: 3.7
Classifier: Programming Language :: Python :: 3.8
Classifier: Programming Language :: Python :: 3.9
Classifier: Programming Language :: Python :: 3.10
License-File: LICENSE
Requires-Dist: aioice-no-netifaces (>=0.7.7post4)
Requires-Dist: cryptography (>=2.2)
Requires-Dist: google-crc32c (>=1.1)
Requires-Dist: pyee (>=9.0.0)
Requires-Dist: pylibsrtp (>=0.5.6)
Requires-Dist: dataclasses ; python_version < "3.7"
Provides-Extra: dev
Requires-Dist: aiohttp (>=3.7.0) ; extra == 'dev'
Requires-Dist: coverage (>=5.0) ; extra == 'dev'
Requires-Dist: numpy (>=1.19.0) ; extra == 'dev'
Requires-Dist: twine ; extra == 'dev'
Requires-Dist: wheel ; extra == 'dev'
